README.rst
setup.py
wutangy/__init__.py
wutangy/__main__.py
wutangy/wutangy.py
wutangy/yapf180966IS.py
wutangy/yapf18096Zp1.py
wutangy.egg-info/PKG-INFO
wutangy.egg-info/SOURCES.txt
wutangy.egg-info/dependency_links.txt
wutangy.egg-info/entry_points.txt
wutangy.egg-info/top_level.txt