Metadata-Version: 1.0
Name: wutangy
Version: 0.0.12.dev0
Summary: wutangy is a WuTang inspired lorem ispsum generator, SUUUUUUUUUU
Home-page: https://github.com/ejmg/wutangy
Author: elias julian marko garcia
Author-email: elias.jm.garcia@gmail.com
License: MIT
Platform: UNKNOWN
